[
  {
    "id" : "1",
    "model_url" : "https://bobile.github.io/ar_models/Happy_Holidays.zip",
    "position" : "1",
    "preview_url" : "https://storage.googleapis.com/babysnap-stag/uploads/thumb_dd4e4aaae4c5f572.jpg",
    "model_name" : "Happy_Holidays"
  },
 {
 "id" : "2",
 "model_url" : "https://bobile.github.io/ar_models/Baloon_rig_v2_orange.zip",
 "position" : "2",
 "preview_url" : "https://storage.googleapis.com/babysnap-stag/uploads/thumb_dd4e4aaae4c5f572.jpg",
 "model_name" : "Baloon_rig_v2_orange"
 },
 {
 "id" : "3",
 "model_url" : "https://bobile.github.io/ar_models/Baloon_rig_v2_pink.zip",
 "position" : "3",
 "preview_url" : "https://storage.googleapis.com/babysnap-stag/uploads/thumb_dd4e4aaae4c5f572.jpg",
 "model_name" : "Baloon_rig_v2_pink"
 },
 {
 "id" : "4",
 "model_url" : "https://bobile.github.io/ar_models/Baloon_rig_v2.zip",
 "position" : "4",
 "preview_url" : "https://storage.googleapis.com/babysnap-stag/uploads/thumb_dd4e4aaae4c5f572.jpg",
 "model_name" : "Baloon_rig_v2"
 },
 {
 "id" : "5",
 "model_url" : "https://bobile.github.io/ar_models/CemeteryCross.zip",
 "position" : "5",
 "preview_url" : "https://storage.googleapis.com/babysnap-stag/uploads/thumb_dd4e4aaae4c5f572.jpg",
 "model_name" : "CemeteryCross"
 },
 {
 "id" : "6",
 "model_url" : "https://bobile.github.io/ar_models/Coffin.zip",
 "position" : "6",
 "preview_url" : "https://storage.googleapis.com/babysnap-stag/uploads/thumb_dd4e4aaae4c5f572.jpg",
 "model_name" : "Coffin"
 },
 {
 "id" : "7",
 "model_url" : "https://bobile.github.io/ar_models/Ghost.zip",
 "position" : "7",
 "preview_url" : "https://storage.googleapis.com/babysnap-stag/uploads/thumb_dd4e4aaae4c5f572.jpg",
 "model_name" : "Ghost"
 },
 {
 "id" : "8",
 "model_url" : "https://bobile.github.io/ar_models/Happy_new_year.zip",
 "position" : "8",
 "preview_url" : "https://storage.googleapis.com/babysnap-stag/uploads/thumb_dd4e4aaae4c5f572.jpg",
 "model_name" : "Happy_new_year"
 },
 {
 "id" : "9",
 "model_url" : "https://bobile.github.io/ar_models/Icecream_rig.zip",
 "position" : "9",
 "preview_url" : "https://storage.googleapis.com/babysnap-stag/uploads/thumb_dd4e4aaae4c5f572.jpg",
 "model_name" : "Icecream_rig"
 },
 {
 "id" : "10",
 "model_url" : "https://bobile.github.io/ar_models/Lollipop_rig.zip",
 "position" : "10",
 "preview_url" : "https://storage.googleapis.com/babysnap-stag/uploads/thumb_dd4e4aaae4c5f572.jpg",
 "model_name" : "Lollipop_rig"
 },
 {
 "id" : "11",
 "model_url" : "https://bobile.github.io/ar_models/Merry_Christmas.zip",
 "position" : "11",
 "preview_url" : "https://storage.googleapis.com/babysnap-stag/uploads/thumb_dd4e4aaae4c5f572.jpg",
 "model_name" : "Merry_Christmas"
 },
 {
 "id" : "12",
 "model_url" : "https://bobile.github.io/ar_models/Pumkin_scale_2.zip",
 "position" : "12",
 "preview_url" : "https://storage.googleapis.com/babysnap-stag/uploads/thumb_dd4e4aaae4c5f572.jpg",
 "model_name" : "Pumkin_scale_2"
 },
 {
 "id" : "13",
 "model_url" : "https://bobile.github.io/ar_models/StoneSkull.zip",
 "position" : "13",
 "preview_url" : "https://storage.googleapis.com/babysnap-stag/uploads/thumb_dd4e4aaae4c5f572.jpg",
 "model_name" : "StoneSkull"
 }
]
